<?xml version = '1.0' encoding = 'UTF-8'?>
<Relation class="oracle.dbtools.crest.model.design.logical.Relation" name="SUC_X_MESA" directorySegmentName="seg_0" id="94F3B31B-9BD6-E97E-03BC-00C7225E47F6">
<createdBy>Jesus</createdBy>
<createdTime>2022-11-18 04:11:12 UTC</createdTime>
<ownerDesignName>tareaAcademica</ownerDesignName>
<engineerTo>
<item key="FF61EF35-73F6-9D60-C83D-5BB6D0F2E003" value="true"/>
</engineerTo>
<sourcePk>3DD8BF62-C070-1968-AE4F-E66B882A584C</sourcePk>
<identifying>false</identifying>
<optionalSource>true</optionalSource>
<optionalTarget>false</optionalTarget>
<sourceCardinality>1</sourceCardinality>
<sourceEntity>BB1CE3E1-A8A2-9201-BADE-F3BC08397BE7</sourceEntity>
<targetCardinalityString>*</targetCardinalityString>
<targetEntity>7BD45BE2-79D9-D733-0FD6-6B3D2DD30B5E</targetEntity>
<transferable>true</transferable>
<deleteRule>NO ACTION</deleteRule>
</Relation>