<?xml version = '1.0' encoding = 'UTF-8'?>
<Relation class="oracle.dbtools.crest.model.design.logical.Relation" name="Relation_37" directorySegmentName="seg_0" id="E5EE500B-847F-0073-F556-3EE30F32ED5E">
<createdBy>Jesus</createdBy>
<createdTime>2022-11-18 16:25:27 UTC</createdTime>
<ownerDesignName>tareaAcademica</ownerDesignName>
<engineerTo>
<item key="FF61EF35-73F6-9D60-C83D-5BB6D0F2E003" value="true"/>
</engineerTo>
<sourcePk>146B5A6A-4DFB-6744-3AB7-C4E018AEDA62</sourcePk>
<identifying>false</identifying>
<optionalSource>true</optionalSource>
<optionalTarget>false</optionalTarget>
<sourceCardinality>1</sourceCardinality>
<sourceEntity>23D2C55A-3959-4FD5-718C-AD10F425CC1D</sourceEntity>
<targetCardinalityString>*</targetCardinalityString>
<targetEntity>BBC0E988-C9E2-1BDA-C31A-D2CEC1477D11</targetEntity>
<transferable>true</transferable>
<deleteRule>NO ACTION</deleteRule>
</Relation>